moear_spider_zhihudaily/__init__.py
moear_spider_zhihudaily/crawler_script.py
moear_spider_zhihudaily/entry.py
moear_spider_zhihudaily/items.py
moear_spider_zhihudaily/middlewares.py
moear_spider_zhihudaily/pipelines.py
moear_spider_zhihudaily/settings.py
moear_spider_zhihudaily/assets/css/package.css
moear_spider_zhihudaily/assets/images/cv_zhihudaily.jpg
moear_spider_zhihudaily/assets/images/mh_zhihudaily.gif
moear_spider_zhihudaily/spiders/__init__.py
moear_spider_zhihudaily/spiders/zhihu_daily.py
moear_spider_zhihudaily-1.1.1.dist-info/METADATA
moear_spider_zhihudaily-1.1.1.dist-info/RECORD
moear_spider_zhihudaily-1.1.1.dist-info/WHEEL
moear_spider_zhihudaily-1.1.1.dist-info/entry_points.txt
moear_spider_zhihudaily-1.1.1.dist-info/top_level.txt
