Metadata-Version: 2.1
Name: moear-spider-zhihudaily
Version: 1.1.1
Summary: MoEar爬虫功能扩展插件 - 知乎日报
Home-page: https://github.com/littlemo/moear-spider-zhihudaily
Author: moear developers
Author-email: moore@moorehy.com
Maintainer: littlemo
Maintainer-email: moore@moorehy.com
License: GPLv3
Project-URL: Source, https://github.com/littlemo/moear-spider-zhihudaily
Project-URL: Tracker, https://github.com/littlemo/moear-spider-zhihudaily/issues
Project-URL: Documentation, http://moear-spider-zhihudaily.rtfd.io/
Keywords: moear scrapy
Platform: UNKNOWN
Classifier: Development Status :: 5 - Production/Stable
Classifier: Environment :: Console
Classifier: Environment :: MacOS X
Classifier: Framework :: Scrapy
Classifier: Framework :: Twisted
Classifier: Intended Audience :: Developers
Classifier: License :: OSI Approved :: GNU General Public License v3 (GPLv3)
Classifier: Natural Language :: Chinese (Simplified)
Classifier: Operating System :: MacOS
Classifier: Operating System :: POSIX :: Linux
Classifier: Programming Language :: Python :: 3
Classifier: Programming Language :: Python :: 3 :: Only
Classifier: Programming Language :: Python :: 3.5
Classifier: Topic :: Communications :: Email
Classifier: Topic :: Documentation :: Sphinx
Classifier: Topic :: Internet
Classifier: Topic :: Software Development :: Version Control :: Git
Classifier: Topic :: Software Development :: Libraries :: Python Modules
Classifier: Topic :: System :: Networking
Classifier: Topic :: Terminals
Classifier: Topic :: Utilities
Requires-Python: >=3
Requires-Dist: Scrapy (~=1.5.0)
Requires-Dist: beautifulsoup4 (~=4.6.0)
Requires-Dist: billiard (~=3.5.0.3)
Requires-Dist: moear-api-common (~=1.0.2)
